odooless/__init__.py
odooless-0.2.5.dist-info/METADATA
odooless-0.2.5.dist-info/WHEEL
odooless-0.2.5.dist-info/top_level.txt
odooless-0.2.5.dist-info/RECORD
