Metadata-Version: 2.1
Name: odooless
Version: 0.2.5
Summary: A DynamoDB ORM inspired by Odoo
Home-page: https://github.com/Barameg/odooless.git
Author: Sam Hasan
Author-email: sam@barameg.co
Keywords: odooless,dynamodb,orm,odoo
Classifier: Development Status :: 3 - Alpha
Classifier: License :: OSI Approved :: MIT License
Classifier: Programming Language :: Python :: 3
Classifier: Programming Language :: Python :: 3.6
Classifier: Programming Language :: Python :: 3.7
Classifier: Programming Language :: Python :: 3.8
Classifier: Programming Language :: Python :: 3.9
Requires-Python: >=3.6
Requires-Dist: boto3
